getbob/__init__.py
getbob-2.0.5.dist-info/METADATA
getbob-2.0.5.dist-info/WHEEL
getbob-2.0.5.dist-info/entry_points.txt
getbob-2.0.5.dist-info/top_level.txt
getbob-2.0.5.dist-info/RECORD
