Metadata-Version: 2.1
Name: getbob
Version: 2.0.5
Summary: Commandline tool to download Defold's Bob
Home-page: UNKNOWN
Author: Mattias.Hedberg
Author-email: hedberg.a.mattias@gmail.com
License: UNKNOWN
Keywords: getbob defold bob game development
Platform: UNKNOWN
Classifier: Development Status :: 4 - Beta
Classifier: Intended Audience :: Developers
Classifier: Topic :: Software Development :: Build Tools
Classifier: License :: OSI Approved :: MIT License
Classifier: Programming Language :: Python :: 3.0
Classifier: Programming Language :: Python :: 3.1
Classifier: Programming Language :: Python :: 3.2
Classifier: Programming Language :: Python :: 3.3
Classifier: Programming Language :: Python :: 3.4
Classifier: Programming Language :: Python :: 3.5
Classifier: Programming Language :: Python :: 3.6
Classifier: Programming Language :: Python :: 3.7
Requires-Python: >=3
Requires-Dist: requests
